README.md
setup.py
sa_notebook_builder/__init__.py
sa_notebook_builder/builder.py
sa_notebook_builder.egg-info/PKG-INFO
sa_notebook_builder.egg-info/SOURCES.txt
sa_notebook_builder.egg-info/dependency_links.txt
sa_notebook_builder.egg-info/top_level.txt