Metadata-Version: 2.1
Name: sa-notebook-builder
Version: 0.1.dev2
Summary: Building jupyter notebooks from code
Home-page: https://github.com/andraskohlmann/sa-notebook-builder
Author: András Kohlmann
Author-email: metuoku@outlook.com
License: UNKNOWN
Platform: UNKNOWN
Classifier: Programming Language :: Python :: 3
Classifier: License :: OSI Approved :: MIT License
Classifier: Operating System :: OS Independent
Requires-Python: >=3.6
